evrpy/__init__.py
evrpy/base_commands.py
evrpy/rpc_calls/__init__.py
evrpy/rpc_calls/addressindex.py
evrpy/rpc_calls/assets.py
evrpy/rpc_calls/blockchain.py
evrpy/rpc_calls/control.py
evrpy/rpc_calls/generating.py
evrpy/rpc_calls/messages.py
evrpy/rpc_calls/mining.py
evrpy/rpc_calls/network.py
evrpy/rpc_calls/rawtransactions.py
evrpy/rpc_calls/restricted.py
evrpy/rpc_calls/restrictedassets.py
evrpy/rpc_calls/rewards.py
evrpy/rpc_calls/util.py
evrpy/rpc_calls/wallet.py
evrpy-0.0.2.dist-info/licenses/LICENSE
evrpy-0.0.2.dist-info/METADATA
evrpy-0.0.2.dist-info/WHEEL
evrpy-0.0.2.dist-info/top_level.txt
evrpy-0.0.2.dist-info/RECORD
