Metadata-Version: 2.4
Name: evrpy
Version: 0.0.2
Summary: Python wrapper for Evrmore RPC CLI
Author-email: neubtrino <neubtrino_evrmore@proton.me>
License: MIT
Project-URL: Homepage, https://github.com/neubtrino/evrpy
Project-URL: Bug Tracker, https://github.com/neubtrino/evrpy/issues
Keywords: evrmore,blockchain,rpc,cli,wrapper,cryptocurrency,crypto
Classifier: Development Status :: 3 - Alpha
Classifier: Intended Audience :: Developers
Classifier: Programming Language :: Python :: 3
Classifier: Programming Language :: Python :: 3.10
Classifier: Programming Language :: Python :: 3 :: Only
Classifier: Operating System :: OS Independent
Classifier: Topic :: Software Development :: Libraries
Classifier: Topic :: Internet
Requires-Python: >=3.10
License-File: LICENSE
Dynamic: license-file
